{
  "meta": {
    "version": "8.0",
    "name": "TradeMind v8.1",
    "mode": "SAFE",
    "updated": "2026-03-06T17:59:44.487486",
    "account": 256085487
  },
  "account": {
    "balance": 1251.85,
    "equity": 1251.85,
    "profit": 0.0,
    "margin": 0.0,
    "free_margin": 1251.85,
    "leverage": 2000,
    "initial_balance": 600
  },
  "zone": {
    "zone": "HUNT",
    "daily_pnl_pct": 0.0,
    "trades_today": 0,
    "wins_today": 0,
    "losses_today": 0,
    "reached_protect": false,
    "consecutive_wins": 0,
    "consecutive_losses": 0,
    "weekly_pnl_pct": -0.0015662115912631336
  },
  "position_manager": {
    "tracked_positions": 0,
    "partial_closed": 0,
    "at_breakeven": 0,
    "trailing_active": 0
  },
  "today": {
    "pnl": 661.26,
    "pnl_pct": 110.21,
    "trades": 7,
    "wins": 4,
    "losses": 3,
    "win_rate": 57.1,
    "target": 2.0,
    "limit": -3.0
  },
  "weekly": {
    "pnl": 657.29,
    "trades": 20,
    "wins": 8,
    "losses": 12,
    "win_rate": 40.0
  },
  "monthly": {
    "pnl": 657.29,
    "trades": 20,
    "wins": 8,
    "losses": 12,
    "win_rate": 40.0,
    "target": 20
  },
  "positions": [],
  "recent_trades": [
    {
      "time": "2026-03-06T17:00:34",
      "symbol": "XAUUSDm",
      "type": "BUY",
      "volume": 0.01,
      "price": 5079.549,
      "pnl": -4.76,
      "comment": ""
    },
    {
      "time": "2026-03-06T17:11:21",
      "symbol": "XAUUSDm",
      "type": "SELL",
      "volume": 0.01,
      "price": 5069.851,
      "pnl": -2.63,
      "comment": ""
    },
    {
      "time": "2026-03-06T17:33:06",
      "symbol": "XAUUSDm",
      "type": "SELL",
      "volume": 0.02,
      "price": 5123.973,
      "pnl": -31.33,
      "comment": "[sl 5123.973]"
    },
    {
      "time": "2026-03-06T17:48:04",
      "symbol": "XAUUSDm",
      "type": "SELL",
      "volume": 0.01,
      "price": 5112.976,
      "pnl": 7.88,
      "comment": ""
    },
    {
      "time": "2026-03-06T17:54:08",
      "symbol": "XAUUSDm",
      "type": "SELL",
      "volume": 0.02,
      "price": 5104.396,
      "pnl": 24.9,
      "comment": ""
    },
    {
      "time": "2026-03-06T17:55:48",
      "symbol": "XAUUSDm",
      "type": "SELL",
      "volume": 0.5,
      "price": 5096.955,
      "pnl": 288.9,
      "comment": ""
    },
    {
      "time": "2026-03-06T17:57:43",
      "symbol": "XAUUSDm",
      "type": "SELL",
      "volume": 0.5,
      "price": 5079.916,
      "pnl": 378.3,
      "comment": ""
    }
  ],
  "total_trades_all_time": 71,
  "features": {
    "hybrid_protection": true,
    "trailing_stop": true,
    "partial_profit": true,
    "ai_analyst": true,
    "edge_cases": 33
  }
}